flatpages_extra/__init__.py
flatpages_extra/admin/__init__.py
flatpages_extra/admin/forms.py
flatpages_extra/admin/models.py
flatpages_extra/admin/views.py
flatpages_extra/apps.py
flatpages_extra/checks.py
flatpages_extra/exceptions.py
flatpages_extra/management/__init__.py
flatpages_extra/management/commands/__init__.py
flatpages_extra/management/commands/flatpages_extra_import_initial.py
flatpages_extra/migrations/0001_initial.py
flatpages_extra/migrations/__init__.py
flatpages_extra/models.py
flatpages_extra/static/admin/flatpages_extra/custom.css
flatpages_extra/static/admin/flatpages_extra/page-fk-widget.js
flatpages_extra/static/admin/flatpages_extra/pygments.css
flatpages_extra/templates/admin/base.html
flatpages_extra/templates/admin/flatpages_extra/flatpage/widgets/content.html
flatpages_extra/templates/admin/flatpages_extra/revision/compare.html
flatpages_extra/templates/admin/flatpages_extra/revision/publish.html
flatpages_extra/templates/admin/flatpages_extra/revision/revert.html
flatpages_extra/urls.py
flatpages_extra/views.py
django_flatpages_extra-1.0.dist-info/WHEEL
django_flatpages_extra-1.0.dist-info/METADATA
django_flatpages_extra-1.0.dist-info/RECORD
