Metadata-Version: 2.3
Name: django-flatpages-extra
Version: 1.0
Summary: A drop-in enhancement for Django's contrib.flatpages
Author: Baptiste Mispelon
Author-email: Baptiste Mispelon <bmispelon@gmail.com>
Classifier: Development Status :: 4 - Beta
Classifier: Framework :: Django
Classifier: Framework :: Django :: 5.0
Classifier: Framework :: Django :: 5.1
Classifier: Framework :: Django :: 5.2
Classifier: Framework :: Django :: 6.0
Requires-Dist: pygments>=2.19.2
Requires-Python: >=3.9
Project-URL: Homepage, https://codeberg.org/bmispelon/django-flatpages-extra
Project-URL: Issues, https://codeberg.org/bmispelon/django-flatpages-extra/issues
Project-URL: Repository, https://codeberg.org/bmispelon/django-flatpages-extra
